MANIFEST.in
README.md
VERSION
requirements.txt
setup.py
dcp_common/__init__.py
dcp_common.egg-info/PKG-INFO
dcp_common.egg-info/SOURCES.txt
dcp_common.egg-info/dependency_links.txt
dcp_common.egg-info/requires.txt
dcp_common.egg-info/top_level.txt
dcp_common/dcp_common/__init__.py
dcp_common/dcp_common/extensions/__init__.py
dcp_common/dcp_common/extensions/scrapy_redis_extension.py
dcp_common/dcp_common/middlewares/__init__.py
dcp_common/dcp_common/middlewares/cookies.py
dcp_common/dcp_common/middlewares/proxy.py
dcp_common/dcp_common/middlewares/useragent.py
dcp_common/dcp_common/pipelines/__init__.py
dcp_common/dcp_common/pipelines/mongodb.py
dcp_common/extensions/__init__.py
dcp_common/extensions/scrapy_redis_extension.py
dcp_common/middlewares/__init__.py
dcp_common/middlewares/cookies.py
dcp_common/middlewares/proxy.py
dcp_common/middlewares/useragent.py
dcp_common/pipelines/__init__.py
dcp_common/pipelines/mongodb.py