Metadata-Version: 1.0
Name: dcp-common
Version: 1.1.5
Summary: Common components for data collector platform.
Home-page: UNKNOWN
Author: UNKNOWN
Author-email: UNKNOWN
License: MIT
Keywords: scrapy-redis,simple
Platform: UNKNOWN
